to_pip.py
bak/__init__.py
bak/app.py
to_pip-3.11.38.dist-info/METADATA
to_pip-3.11.38.dist-info/WHEEL
to_pip-3.11.38.dist-info/entry_points.txt
to_pip-3.11.38.dist-info/top_level.txt
to_pip-3.11.38.dist-info/RECORD
