Metadata-Version: 2.1
Name: to-pip
Version: 3.11.38
Requires-Dist: wheel
Requires-Dist: setuptools
Requires-Dist: twine
Requires-Dist: python-dotenv
Requires-Dist: build
